LICENSE
MANIFEST.in
README.rst
cirpy.py
cirpy_test.py
setup.py
CIRpy.egg-info/PKG-INFO
CIRpy.egg-info/SOURCES.txt
CIRpy.egg-info/dependency_links.txt
CIRpy.egg-info/requires.txt
CIRpy.egg-info/top_level.txt
docs/Makefile
docs/README.rst
docs/source/api.rst
docs/source/conf.py
docs/source/index.rst
docs/source/guide/contributing.rst
docs/source/guide/gettingstarted.rst
docs/source/guide/install.rst
docs/source/guide/misc.rst
docs/source/guide/query.rst
docs/source/guide/resolvers.rst
requirements/common.txt
requirements/dev.txt